ob_fact/__init__.py
opsbeacon_fact-0.1.dist-info/METADATA
opsbeacon_fact-0.1.dist-info/WHEEL
opsbeacon_fact-0.1.dist-info/top_level.txt
opsbeacon_fact-0.1.dist-info/RECORD
