Metadata-Version: 2.1
Name: opsbeacon-fact
Version: 0.1
Summary: A simple package to calculate factorial
Author: obsevket
Author-email: mserdogmus@opsbeacon.com
